<?xml version="1.0" encoding="utf-8"?>
<EquipTemplateInfo>
  <EquipTemplate EquipTemplateId="181" EquipTemplateName="KSTAR-YDC9106" EquipTemplateType="10000" EquipBaseTemplateId="-1" ParentTemplateId="-1" Property="0" LibName="KSTAR-YDC9106" TemplateCode="" TemplateLog="" Description="" LastUpdateTime="20150831045924">
    <Signals>
      <EquipSignal SignalId="1" SignalName="输入电压" SignalBaseId="-1" SignalType="0" SignalProperty="0" ChannelNo="0" Expression="" DataType="0" ShowPrecision="0.0" Unit="V" StoreInterval="0" AbsValueThreshold="0" PercentThreshold="0" StatisticPeriod="0" Enable="true" Description="">
        <Meanings />
      </EquipSignal>
      <EquipSignal SignalId="2" SignalName="异常输入电压" SignalBaseId="-1" SignalType="0" SignalProperty="0" ChannelNo="1" Expression="" DataType="0" ShowPrecision="0.0" Unit="V" StoreInterval="0" AbsValueThreshold="0" PercentThreshold="0" StatisticPeriod="0" Enable="true" Description="">
        <Meanings />
      </EquipSignal>
      <EquipSignal SignalId="3" SignalName="输出电压" SignalBaseId="-1" SignalType="0" SignalProperty="0" ChannelNo="2" Expression="" DataType="0" ShowPrecision="0.0" Unit="V" StoreInterval="0" AbsValueThreshold="0" PercentThreshold="0" StatisticPeriod="0" Enable="true" Description="">
        <Meanings />
      </EquipSignal>
      <EquipSignal SignalId="4" SignalName="负载率" SignalBaseId="-1" SignalType="0" SignalProperty="0" ChannelNo="3" Expression="" DataType="0" ShowPrecision="0.0" Unit="A" StoreInterval="0" AbsValueThreshold="0" PercentThreshold="0" StatisticPeriod="0" Enable="true" Description="">
        <Meanings />
      </EquipSignal>
      <EquipSignal SignalId="5" SignalName="输入频率" SignalBaseId="-1" SignalType="0" SignalProperty="0" ChannelNo="4" Expression="" DataType="0" ShowPrecision="0.0" Unit="Hz" StoreInterval="0" AbsValueThreshold="0" PercentThreshold="0" StatisticPeriod="0" Enable="true" Description="">
        <Meanings />
      </EquipSignal>
      <EquipSignal SignalId="6" SignalName="电池单体电压" SignalBaseId="-1" SignalType="0" SignalProperty="0" ChannelNo="5" Expression="" DataType="0" ShowPrecision="0.0" Unit="V" StoreInterval="0" AbsValueThreshold="0" PercentThreshold="0" StatisticPeriod="0" Enable="true" Description="">
        <Meanings />
      </EquipSignal>
      <EquipSignal SignalId="7" SignalName="温度" SignalBaseId="-1" SignalType="0" SignalProperty="0" ChannelNo="6" Expression="" DataType="0" ShowPrecision="0.0" Unit="℃" StoreInterval="0" AbsValueThreshold="0" PercentThreshold="0" StatisticPeriod="0" Enable="true" Description="">
        <Meanings />
      </EquipSignal>
      <EquipSignal SignalId="8" SignalName="主路异常" SignalBaseId="-1" SignalType="1" SignalProperty="0" ChannelNo="7" Expression="" DataType="0" ShowPrecision="0" Unit="" StoreInterval="0" AbsValueThreshold="0" PercentThreshold="0" StatisticPeriod="0" Enable="true" Description="">
        <Meanings>
          <SignalMeaning StateValue="1" Meaning="有告警" />
          <SignalMeaning StateValue="0" Meaning="无告警" />
        </Meanings>
      </EquipSignal>
      <EquipSignal SignalId="9" SignalName="电池电压低" SignalBaseId="-1" SignalType="1" SignalProperty="0" ChannelNo="8" Expression="" DataType="0" ShowPrecision="0" Unit="" StoreInterval="0" AbsValueThreshold="1" PercentThreshold="0" StatisticPeriod="0" Enable="true" Description="">
        <Meanings>
          <SignalMeaning StateValue="0" Meaning="无告警" />
          <SignalMeaning StateValue="1" Meaning="有告警" />
        </Meanings>
      </EquipSignal>
      <EquipSignal SignalId="10" SignalName="旁路/整流器启动" SignalBaseId="-1" SignalType="1" SignalProperty="0" ChannelNo="9" Expression="" DataType="0" ShowPrecision="0" Unit="" StoreInterval="0" AbsValueThreshold="0" PercentThreshold="0" StatisticPeriod="0" Enable="true" Description="">
        <Meanings>
          <SignalMeaning StateValue="0" Meaning="否" />
          <SignalMeaning StateValue="1" Meaning="是" />
        </Meanings>
      </EquipSignal>
      <EquipSignal SignalId="11" SignalName="UPS故障" SignalBaseId="-1" SignalType="1" SignalProperty="0" ChannelNo="10" Expression="" DataType="0" ShowPrecision="0" Unit="" StoreInterval="0" AbsValueThreshold="0" PercentThreshold="0" StatisticPeriod="0" Enable="true" Description="">
        <Meanings>
          <SignalMeaning StateValue="1" Meaning="有告警" />
          <SignalMeaning StateValue="0" Meaning="无告警" />
        </Meanings>
      </EquipSignal>
      <EquipSignal SignalId="12" SignalName="UPS状态" SignalBaseId="-1" SignalType="1" SignalProperty="0" ChannelNo="11" Expression="" DataType="0" ShowPrecision="0" Unit="" StoreInterval="0" AbsValueThreshold="1" PercentThreshold="0" StatisticPeriod="0" Enable="true" Description="">
        <Meanings>
          <SignalMeaning StateValue="1" Meaning="在线" />
          <SignalMeaning StateValue="0" Meaning="待机" />
        </Meanings>
      </EquipSignal>
      <EquipSignal SignalId="13" SignalName="自检进行中" SignalBaseId="-1" SignalType="1" SignalProperty="0" ChannelNo="12" Expression="" DataType="0" ShowPrecision="0" Unit="" StoreInterval="0" AbsValueThreshold="1" PercentThreshold="0" StatisticPeriod="0" Enable="true" Description="">
        <Meanings>
          <SignalMeaning StateValue="0" Meaning="否" />
          <SignalMeaning StateValue="1" Meaning="是" />
        </Meanings>
      </EquipSignal>
      <EquipSignal SignalId="14" SignalName="启动关机" SignalBaseId="-1" SignalType="1" SignalProperty="0" ChannelNo="13" Expression="" DataType="0" ShowPrecision="0" Unit="" StoreInterval="0" AbsValueThreshold="1" PercentThreshold="0" StatisticPeriod="0" Enable="true" Description="">
        <Meanings>
          <SignalMeaning StateValue="0" Meaning="否" />
          <SignalMeaning StateValue="1" Meaning="是" />
        </Meanings>
      </EquipSignal>
      <EquipSignal SignalId="15" SignalName="蜂鸣器状态" SignalBaseId="-1" SignalType="1" SignalProperty="0" ChannelNo="14" Expression="" DataType="0" ShowPrecision="0" Unit="" StoreInterval="0" AbsValueThreshold="1" PercentThreshold="0" StatisticPeriod="0" Enable="true" Description="">
        <Meanings />
      </EquipSignal>
      <EquipSignal SignalId="16" SignalName="输入电压" SignalBaseId="-1" SignalType="0" SignalProperty="0" ChannelNo="15" Expression="" DataType="0" ShowPrecision="0.0" Unit="V" StoreInterval="0" AbsValueThreshold="1" PercentThreshold="0" StatisticPeriod="0" Enable="true" Description="">
        <Meanings />
      </EquipSignal>
      <EquipSignal SignalId="17" SignalName="输入频率" SignalBaseId="-1" SignalType="0" SignalProperty="0" ChannelNo="16" Expression="" DataType="0" ShowPrecision="0.0" Unit="Hz" StoreInterval="0" AbsValueThreshold="0" PercentThreshold="0" StatisticPeriod="0" Enable="true" Description="">
        <Meanings />
      </EquipSignal>
      <EquipSignal SignalId="20" SignalName="输出电压" SignalBaseId="-1" SignalType="0" SignalProperty="0" ChannelNo="19" Expression="" DataType="0" ShowPrecision="0.0" Unit="V" StoreInterval="0" AbsValueThreshold="1" PercentThreshold="0" StatisticPeriod="0" Enable="true" Description="">
        <Meanings />
      </EquipSignal>
      <EquipSignal SignalId="21" SignalName="输出频率" SignalBaseId="-1" SignalType="0" SignalProperty="0" ChannelNo="20" Expression="" DataType="0" ShowPrecision="0.0" Unit="Hz" StoreInterval="0" AbsValueThreshold="0" PercentThreshold="0" StatisticPeriod="0" Enable="true" Description="">
        <Meanings />
      </EquipSignal>
      <EquipSignal SignalId="22" SignalName="输出电流" SignalBaseId="-1" SignalType="0" SignalProperty="0" ChannelNo="21" Expression="" DataType="0" ShowPrecision="0.0" Unit="A" StoreInterval="0" AbsValueThreshold="0" PercentThreshold="0" StatisticPeriod="0" Enable="true" Description="">
        <Meanings />
      </EquipSignal>
      <EquipSignal SignalId="23" SignalName="输出功因" SignalBaseId="-1" SignalType="0" SignalProperty="0" ChannelNo="22" Expression="" DataType="0" ShowPrecision="0.0" Unit="" StoreInterval="0" AbsValueThreshold="0" PercentThreshold="0" StatisticPeriod="0" Enable="true" Description="">
        <Meanings />
      </EquipSignal>
      <EquipSignal SignalId="24" SignalName="负载率" SignalBaseId="-1" SignalType="0" SignalProperty="0" ChannelNo="23" Expression="" DataType="0" ShowPrecision="0.0" Unit="" StoreInterval="0" AbsValueThreshold="0" PercentThreshold="0" StatisticPeriod="0" Enable="true" Description="">
        <Meanings />
      </EquipSignal>
      <EquipSignal SignalId="25" SignalName="负载峰值比" SignalBaseId="-1" SignalType="0" SignalProperty="0" ChannelNo="24" Expression="" DataType="0" ShowPrecision="0.0" Unit="" StoreInterval="0" AbsValueThreshold="0" PercentThreshold="0" StatisticPeriod="0" Enable="true" Description="">
        <Meanings />
      </EquipSignal>
      <EquipSignal SignalId="26" SignalName="旁路电压" SignalBaseId="-1" SignalType="0" SignalProperty="0" ChannelNo="25" Expression="" DataType="0" ShowPrecision="0.0" Unit="V" StoreInterval="0" AbsValueThreshold="1" PercentThreshold="0" StatisticPeriod="0" Enable="true" Description="">
        <Meanings />
      </EquipSignal>
      <EquipSignal SignalId="27" SignalName="旁路频率" SignalBaseId="-1" SignalType="0" SignalProperty="0" ChannelNo="26" Expression="" DataType="0" ShowPrecision="0.0" Unit="Hz" StoreInterval="0" AbsValueThreshold="0" PercentThreshold="0" StatisticPeriod="0" Enable="true" Description="">
        <Meanings />
      </EquipSignal>
      <EquipSignal SignalId="28" SignalName="正BUS电压" SignalBaseId="-1" SignalType="0" SignalProperty="0" ChannelNo="27" Expression="" DataType="0" ShowPrecision="0.0" Unit="V" StoreInterval="0" AbsValueThreshold="1" PercentThreshold="0" StatisticPeriod="0" Enable="true" Description="">
        <Meanings />
      </EquipSignal>
      <EquipSignal SignalId="29" SignalName="负BUS电压" SignalBaseId="-1" SignalType="0" SignalProperty="0" ChannelNo="28" Expression="" DataType="0" ShowPrecision="0.0" Unit="V" StoreInterval="0" AbsValueThreshold="1" PercentThreshold="0" StatisticPeriod="0" Enable="true" Description="">
        <Meanings />
      </EquipSignal>
      <EquipSignal SignalId="30" SignalName="正电池组电压" SignalBaseId="-1" SignalType="0" SignalProperty="0" ChannelNo="29" Expression="" DataType="0" ShowPrecision="0.0" Unit="V" StoreInterval="0" AbsValueThreshold="1" PercentThreshold="0" StatisticPeriod="0" Enable="true" Description="">
        <Meanings />
      </EquipSignal>
      <EquipSignal SignalId="31" SignalName="负电池组电压" SignalBaseId="-1" SignalType="0" SignalProperty="0" ChannelNo="30" Expression="" DataType="0" ShowPrecision="0.0" Unit="V" StoreInterval="0" AbsValueThreshold="1" PercentThreshold="0" StatisticPeriod="0" Enable="true" Description="">
        <Meanings />
      </EquipSignal>
      <EquipSignal SignalId="32" SignalName="正电池组电流" SignalBaseId="-1" SignalType="0" SignalProperty="0" ChannelNo="31" Expression="" DataType="0" ShowPrecision="0.0" Unit="A" StoreInterval="0" AbsValueThreshold="0" PercentThreshold="0" StatisticPeriod="0" Enable="true" Description="">
        <Meanings />
      </EquipSignal>
      <EquipSignal SignalId="33" SignalName="负电池组电流" SignalBaseId="-1" SignalType="0" SignalProperty="0" ChannelNo="32" Expression="" DataType="0" ShowPrecision="0.0" Unit="A" StoreInterval="0" AbsValueThreshold="0" PercentThreshold="0" StatisticPeriod="0" Enable="true" Description="">
        <Meanings />
      </EquipSignal>
      <EquipSignal SignalId="34" SignalName="有功功率" SignalBaseId="-1" SignalType="0" SignalProperty="0" ChannelNo="33" Expression="" DataType="0" ShowPrecision="0.0" Unit="" StoreInterval="0" AbsValueThreshold="0" PercentThreshold="0" StatisticPeriod="0" Enable="true" Description="">
        <Meanings />
      </EquipSignal>
      <EquipSignal SignalId="35" SignalName="视在功率" SignalBaseId="-1" SignalType="0" SignalProperty="0" ChannelNo="34" Expression="" DataType="0" ShowPrecision="0.0" Unit="" StoreInterval="0" AbsValueThreshold="0" PercentThreshold="0" StatisticPeriod="0" Enable="true" Description="">
        <Meanings />
      </EquipSignal>
      <EquipSignal SignalId="36" SignalName="运行状态" SignalBaseId="-1" SignalType="1" SignalProperty="0" ChannelNo="17" Expression="" DataType="0" ShowPrecision="0" Unit="" StoreInterval="0" AbsValueThreshold="0" PercentThreshold="0" StatisticPeriod="0" Enable="true" Description="">
        <Meanings>
          <SignalMeaning StateValue="1" Meaning="初始化" />
          <SignalMeaning StateValue="2" Meaning="待机状态" />
          <SignalMeaning StateValue="3" Meaning="无输出状态" />
          <SignalMeaning StateValue="4" Meaning="旁路状态" />
          <SignalMeaning StateValue="5" Meaning="市电状态" />
          <SignalMeaning StateValue="6" Meaning="电池状态" />
          <SignalMeaning StateValue="7" Meaning="电池自检状态" />
          <SignalMeaning StateValue="8" Meaning="逆变启动中" />
          <SignalMeaning StateValue="9" Meaning="经济模式" />
          <SignalMeaning StateValue="10" Meaning="EPO状态" />
          <SignalMeaning StateValue="11" Meaning="维护旁路模式" />
          <SignalMeaning StateValue="12" Meaning="故障模式" />
        </Meanings>
      </EquipSignal>
      <EquipSignal SignalId="10001" SignalName="设备通讯状态" SignalBaseId="-1" SignalType="1" SignalProperty="0" ChannelNo="-1" Expression="" DataType="0" ShowPrecision="0" Unit="" StoreInterval="0" AbsValueThreshold="0" PercentThreshold="0" StatisticPeriod="0" Enable="true" Description="">
        <Meanings>
          <SignalMeaning StateValue="1" Meaning="通讯正常" />
          <SignalMeaning StateValue="0" Meaning="通讯中断" />
        </Meanings>
      </EquipSignal>
    </Signals>
    <Events>
      <EquipEvent EventId="8" EventName="主路异常" EventBaseId="-1" EventType="0" RelatedSignalId="-1" StartExpression="[-1,8]" SuppressExpression="" Reversal="0" Enable="true" Description="">
        <Conditions>
          <EventCondition ConditionId="0" Meaning="有告警" EventSeverity="1" StartOperation="=" StartCompareValue="1" StartDelay="0" EndOperation="" EndCompareValue="" EndDelay="0" Frequency="0" FreqThreshold="0" />
        </Conditions>
      </EquipEvent>
      <EquipEvent EventId="9" EventName="电池电压低" EventBaseId="-1" EventType="0" RelatedSignalId="-1" StartExpression="[-1,9]" SuppressExpression="" Reversal="0" Enable="true" Description="">
        <Conditions>
          <EventCondition ConditionId="0" Meaning="有告警" EventSeverity="1" StartOperation="=" StartCompareValue="1" StartDelay="0" EndOperation="" EndCompareValue="" EndDelay="0" Frequency="0" FreqThreshold="0" />
        </Conditions>
      </EquipEvent>
      <EquipEvent EventId="11" EventName="UPS故障" EventBaseId="-1" EventType="0" RelatedSignalId="-1" StartExpression="[-1,11]" SuppressExpression="" Reversal="0" Enable="true" Description="">
        <Conditions>
          <EventCondition ConditionId="0" Meaning="有告警" EventSeverity="1" StartOperation="=" StartCompareValue="1" StartDelay="0" EndOperation="" EndCompareValue="" EndDelay="0" Frequency="0" FreqThreshold="0" />
        </Conditions>
      </EquipEvent>
      <EquipEvent EventId="10001" EventName="设备通讯状态" EventBaseId="-1" EventType="0" RelatedSignalId="-1" StartExpression="[-1,10001]" SuppressExpression="" Reversal="0" Enable="true" Description="">
        <Conditions>
          <EventCondition ConditionId="1" Meaning="通讯中断" EventSeverity="2" StartOperation="=" StartCompareValue="0" StartDelay="5" EndOperation="" EndCompareValue="" EndDelay="5" Frequency="0" FreqThreshold="0" />
        </Conditions>
      </EquipEvent>
    </Events>
    <Commands>
      <EquipCommand CommandId="1" CommandName="几分钟后关机" CommandBaseId="-1" CommandType="1" ControlType="0" RelatedSignalId="-1" CommandToken="10" Priority="0" Timeout="0" Retry="0" Enable="true" Description="">
        <CommandParameter ParameterId="1" ParameterName="关机" UIControlType="1" DataType="0" DefaultValue="0" MaxValue="0" MinValue="0">
          <CommandMeaning ParameterValue="0" Meaning="0min后关机" />
          <CommandMeaning ParameterValue="1" Meaning="1min后关机" />
          <CommandMeaning ParameterValue="2" Meaning="2min后关机" />
          <CommandMeaning ParameterValue="3" Meaning="3min后关机" />
          <CommandMeaning ParameterValue="5" Meaning="5min后关机" />
          <CommandMeaning ParameterValue="8" Meaning="8min后关机" />
        </CommandParameter>
      </EquipCommand>
      <EquipCommand CommandId="2" CommandName="几分钟后开机" CommandBaseId="-1" CommandType="1" ControlType="0" RelatedSignalId="-1" CommandToken="11" Priority="0" Timeout="0" Retry="0" Enable="true" Description="">
        <CommandParameter ParameterId="1" ParameterName="写电池并联组数" UIControlType="1" DataType="0" DefaultValue="0" MaxValue="0" MinValue="0">
          <CommandMeaning ParameterValue="0" Meaning="0min后开机" />
          <CommandMeaning ParameterValue="1" Meaning="1min后开机" />
          <CommandMeaning ParameterValue="2" Meaning="2min后开机" />
          <CommandMeaning ParameterValue="3" Meaning="3min后开机" />
          <CommandMeaning ParameterValue="4" Meaning="4min后开机" />
          <CommandMeaning ParameterValue="5" Meaning="5min后开机" />
        </CommandParameter>
      </EquipCommand>
      <EquipCommand CommandId="3" CommandName="关闭/开启蜂鸣器" CommandBaseId="-1" CommandType="1" ControlType="0" RelatedSignalId="-1" CommandToken="12" Priority="0" Timeout="0" Retry="0" Enable="true" Description="">
        <CommandParameter ParameterId="1" ParameterName="关闭/开启蜂鸣器" UIControlType="1" DataType="0" DefaultValue="0" MaxValue="0" MinValue="0">
          <CommandMeaning ParameterValue="0" Meaning="关闭" />
          <CommandMeaning ParameterValue="1" Meaning="开启" />
        </CommandParameter>
      </EquipCommand>
      <EquipCommand CommandId="4" CommandName="test-控制信号" CommandBaseId="" CommandType="0" ControlType="0" RelatedSignalId="" CommandToken="15" Priority="0" Timeout="0" Retry="0" Enable="true" Description="">
        <CommandParameter ParameterId="1" ParameterName="设置ups供电模式" UIControlType="0" DataType="0" DefaultValue="0" MaxValue="0" MinValue="0" />
      </EquipCommand>
    </Commands>
  </EquipTemplate>
</EquipTemplateInfo>